tiledtmxloader/__init__.py
tiledtmxloader/helperspygame.py
tiledtmxloader/helperspyglet.py
tiledtmxloader/tmxreader.py
tiledtmxloader-3.1.0.131.dist-info/LICENSE.txt
tiledtmxloader-3.1.0.131.dist-info/METADATA
tiledtmxloader-3.1.0.131.dist-info/WHEEL
tiledtmxloader-3.1.0.131.dist-info/top_level.txt
tiledtmxloader-3.1.0.131.dist-info/RECORD
